create_pypi_cli/__init__.py
create_pypi_cli/main.py
create_pypi_cli/templates/.gitignore
create_pypi_cli/templates/.isort.cfg
create_pypi_cli/templates/.pre-commit-config.yaml
create_pypi_cli/templates/README.md
create_pypi_cli/templates/__init__.py
create_pypi_cli/templates/requirements.txt
create_pypi_cli/templates/setup.py
create_pypi_cli/templates/.github/workflows/main.yml
create_pypi_cli-0.2.6.dist-info/METADATA
create_pypi_cli-0.2.6.dist-info/WHEEL
create_pypi_cli-0.2.6.dist-info/entry_points.txt
create_pypi_cli-0.2.6.dist-info/top_level.txt
create_pypi_cli-0.2.6.dist-info/RECORD
